spice_kernels/__init__.py
spice_kernels/astro.py
spice_kernels/cubes.py
spice_kernels/limb_fit.py
spice_kernels/movie.py
spice_kernels/movie_read_fits.py
spice_kernels/orbit_cdf.py
spice_kernels/spice_kernels.py
spice_kernels/util.py
spice_kernels-0.1.7.dist-info/entry_points.txt
spice_kernels-0.1.7.dist-info/WHEEL
spice_kernels-0.1.7.dist-info/METADATA
spice_kernels-0.1.7.dist-info/RECORD
